charex/__init__.py
charex/__main__.py
charex/charex.py
charex/charsets.py
charex/cmds.py
charex/db.py
charex/denormal.py
charex/escape.py
charex/gui.py
charex/http.py
charex/normal.py
charex/shell.py
charex/util.py
charex/data/__init__.py
charex/data/entities.json
charex/data/help_xt.txt
charex/data/path_map.json
charex/data/prop_map.json
charex/data/quote.html
charex/data/result.html
charex/data/sources.json
charex/data/v14_0/Denormal.zip
charex/data/v14_0/UCD.zip
charex/data/v14_0/Unihan.zip
charex/data/v14_0/idna2008.txt
charex/data/v14_0/sources.json
charex/data/v15_0/Denormal.zip
charex/data/v15_0/UCD.zip
charex/data/v15_0/Unihan.zip
charex/data/v15_0/idna2008.txt
charex/data/v15_0/sources.json
charex/data/v15_1/Denormal.zip
charex/data/v15_1/UCD.zip
charex/data/v15_1/Unihan.zip
charex/data/v15_1/idna2008.txt
charex/data/v15_1/sources.json
charex-0.2.3.dist-info/licenses/LICENSE
charex-0.2.3.dist-info/METADATA
charex-0.2.3.dist-info/WHEEL
charex-0.2.3.dist-info/entry_points.txt
charex-0.2.3.dist-info/top_level.txt
charex-0.2.3.dist-info/RECORD
