Metadata-Version: 2.4
Name: charex
Version: 0.2.3
Summary: A unicode and character set explorer.
Author-email: "Paul J. Iutzi" <pji@mac.com>
Project-URL: Homepage, https://charex.readthedocs.io/en/latest/index.html#
Project-URL: Documentation, https://charex.readthedocs.io/en/latest/index.html#
Project-URL: Source, https://github.com/pji/charex
Classifier: Programming Language :: Python :: 3
Classifier: License :: OSI Approved :: MIT License
Classifier: Operating System :: OS Independent
Requires-Python: >=3.11
License-File: LICENSE
Requires-Dist: flask
Requires-Dist: blessed
Dynamic: license-file
